README.rst
setup.py
syglass/AudioStreamShared.dll
syglass/CloudXRClient_3.dll
syglass/ElastixImageFilter-2.0.dll
syglass/ITKCommon-5.1.dll
syglass/ITKIOBMP-5.1.dll
syglass/ITKIOBioRad-5.1.dll
syglass/ITKIOBruker-5.1.dll
syglass/ITKIOGDCM-5.1.dll
syglass/ITKIOGE-5.1.dll
syglass/ITKIOGIPL-5.1.dll
syglass/ITKIOHDF5-5.1.dll
syglass/ITKIOIPL-5.1.dll
syglass/ITKIOImageBase-5.1.dll
syglass/ITKIOJPEG-5.1.dll
syglass/ITKIOJPEG2000-5.1.dll
syglass/ITKIOLSM-5.1.dll
syglass/ITKIOMINC-5.1.dll
syglass/ITKIOMRC-5.1.dll
syglass/ITKIOMeshBYU-5.1.dll
syglass/ITKIOMeshBase-5.1.dll
syglass/ITKIOMeshFreeSurfer-5.1.dll
syglass/ITKIOMeshGifti-5.1.dll
syglass/ITKIOMeshOBJ-5.1.dll
syglass/ITKIOMeshOFF-5.1.dll
syglass/ITKIOMeshVTK-5.1.dll
syglass/ITKIOMeta-5.1.dll
syglass/ITKIONIFTI-5.1.dll
syglass/ITKIONRRD-5.1.dll
syglass/ITKIOPNG-5.1.dll
syglass/ITKIOStimulate-5.1.dll
syglass/ITKIOTIFF-5.1.dll
syglass/ITKIOTransformBase-5.1.dll
syglass/ITKIOTransformHDF5-5.1.dll
syglass/ITKIOTransformInsightLegacy-5.1.dll
syglass/ITKIOTransformMatlab-5.1.dll
syglass/ITKIOVTK-5.1.dll
syglass/ITKOptimizers-5.1.dll
syglass/ITKSmoothing-5.1.dll
syglass/ITKSpatialObjects-5.1.dll
syglass/ITKStatistics-5.1.dll
syglass/ITKTransform-5.1.dll
syglass/Idaldll.dll
syglass/InputStreamShared.dll
syglass/LoggingLibrary64.dll
syglass/Nd2File.dll
syglass/Nd2ReadSdk.dll
syglass/NvStreamBase.dll
syglass/OpenAL32.dll
syglass/Poco.dll
syglass/SBReadFile.dll
syglass/SDL2.dll
syglass/SimpleITKBasicFilters0-2.0.dll
syglass/SimpleITKCommon-2.0.dll
syglass/SimpleITKIO-2.0.dll
syglass/SimpleITK_ITKCommon-2.0.dll
syglass/SimpleITK_ITKImageIntensity-2.0.dll
syglass/StreamClientShared.dll
syglass/TKBRep.dll
syglass/TKG2d.dll
syglass/TKG3d.dll
syglass/TKGeomAlgo.dll
syglass/TKGeomBase.dll
syglass/TKMath.dll
syglass/TKMesh.dll
syglass/TKSTEP.dll
syglass/TKSTEP209.dll
syglass/TKSTEPAttr.dll
syglass/TKSTEPBase.dll
syglass/TKShHealing.dll
syglass/TKTopAlgo.dll
syglass/TKXSBase.dll
syglass/TKernel.dll
syglass/VsiPluginForIdal.dll
syglass.egg-info/PKG-INFO
syglass.egg-info/SOURCES.txt
syglass.egg-info/dependency_links.txt
syglass.egg-info/requires.txt
syglass.egg-info/top_level.txt