Metadata-Version: 2.1
Name: syglass
Version: 0.78
Summary: syGlass Python API
Home-page: https://syglass.io
Author: syGlass
Author-email: info@syglass.io
Classifier: Development Status :: 3 - Alpha
Classifier: Environment :: Win32 (MS Windows)
Requires-Python: >=3.4
Requires-Dist: numpy<2.0.0
